lazy/__init__.py
lazy/lazy.py
lazy/lazy.pyi
lazy/py.typed
lazy-1.6.dist-info/LICENSE
lazy-1.6.dist-info/METADATA
lazy-1.6.dist-info/WHEEL
lazy-1.6.dist-info/top_level.txt
lazy-1.6.dist-info/RECORD
