Metadata-Version: 2.1
Name: lazy
Version: 1.6
Summary: Lazy attributes for Python objects
Home-page: https://github.com/stefanholek/lazy
Author: Stefan H. Holek
Author-email: stefan@epy.co.at
License: BSD-2-Clause
Project-URL: Documentation, https://lazy.readthedocs.io/en/stable/
Keywords: decorator,lazy,lazy attribute,descriptor,property
Classifier: Development Status :: 5 - Production/Stable
Classifier: Intended Audience :: Developers
Classifier: License :: OSI Approved :: BSD License
Classifier: Operating System :: OS Independent
Classifier: Programming Language :: Python
Classifier: Programming Language :: Python :: 2
Classifier: Programming Language :: Python :: 3
Requires-Python: !=3.0.*,!=3.1.*,!=3.2.*,!=3.3.*,>=2.7
Provides-Extra: mypy
Provides-Extra: docs
License-File: LICENSE
